pgcrud/__init__.py
pgcrud/connector.py
pgcrud-0.0.6.dist-info/LICENSE
pgcrud-0.0.6.dist-info/METADATA
pgcrud-0.0.6.dist-info/WHEEL
pgcrud-0.0.6.dist-info/top_level.txt
pgcrud-0.0.6.dist-info/RECORD
