Metadata-Version: 2.1
Name: pgcrud
Version: 0.0.6
Summary: A package to perform Postgres CRUD operations
Home-page: https://gitlab.com/wjwatkinson/pgcrud
Author: Will Watkinson
Author-email: wjwats4295@gmail.com
License: UNKNOWN
Platform: UNKNOWN
Classifier: Programming Language :: Python :: 3
Classifier: License :: OSI Approved :: MIT License
Classifier: Operating System :: OS Independent
Requires-Python: >=3.6
Requires-Dist: psycopg2
